Workbook

Sheet Tabla de Amorticación
D1: Tabla de Amortización del Crédito
A3: Línea de Crédito | C3: 1000000
A4: Tasa del Crédito (Anual) | C4: 0.12
A5: Tiempo (n) | B5: meses | C5: 24
A6: Tasa Comisión por Apertura | C6: 0.02 | I6: Tasa Efectiva (anualizada) | K6: 0.1594004
A7: Pagar Seguro (Anual) | C7: 10000
A8: Pago Mensual | C8: =- PMT(C4 / 12,C5,C3,0,0) -> 47073.472 | D8: =C3 / ( (1 - (1+C4/12)^(-C5) ) / (C4/12) ) -> 47073.472 | K8: Flujos Totales
K9: =SUM(K11:K34) -> 1000000
A10: Tiempo | B10: SI Inicio | C10: Tasa | D10: Pago = Cap + Int | E10: Intereses | F10: Pago a Capital | G10: SI Final | H10: Comisión por Apertura | I10: Seguro de Vida | J10: Pago Final | K10: Flujos a VP
A11: 1 | B11: =C3 -> 1000000 | C11: =$C$4 / 12 -> 0.01 | D11: =$C$8 -> 47073.472 | E11: =B11 * C11 -> 10000 | F11: =D11 - E11 -> 37073.472 | G11: =B11 - F11 -> 962926.53 | H11: =C3 * C6 -> 20000 | I11: =C7 -> 10000 | J11: =D11 + H11 + I11 -> 77073.472 | K11: =J11 / (1 + $K$6/12)^A11 -> 76063.098
A12: =+A11+1 -> 2 | B12: =G11 -> 962926.53 | C12: =$C$4 / 12 -> 0.01 | D12: =$C$8 -> 47073.472 | E12: =B12 * C12 -> 9629.2653 | F12: =D12 - E12 -> 37444.207 | G12: =B12 - F12 -> 925482.32 | J12: =D12 + H12 + I12 -> 47073.472 | K12: =J12 / (1 + $K$6/12)^A12 -> 45847.368
A13: =+A12+1 -> 3 | B13: =G12 -> 925482.32 | C13: =$C$4 / 12 -> 0.01 | D13: =$C$8 -> 47073.472 | E13: =B13 * C13 -> 9254.8232 | F13: =D13 - E13 -> 37818.649 | G13: =B13 - F13 -> 887663.67 | J13: =D13 + H13 + I13 -> 47073.472 | K13: =J13 / (1 + $K$6/12)^A13 -> 45246.344
A14: =+A13+1 -> 4 | B14: =G13 -> 887663.67 | C14: =$C$4 / 12 -> 0.01 | D14: =$C$8 -> 47073.472 | E14: =B14 * C14 -> 8876.6367 | F14: =D14 - E14 -> 38196.836 | G14: =B14 - F14 -> 849466.84 | J14: =D14 + H14 + I14 -> 47073.472 | K14: =J14 / (1 + $K$6/12)^A14 -> 44653.199
A15: =+A14+1 -> 5 | B15: =G14 -> 849466.84 | C15: =$C$4 / 12 -> 0.01 | D15: =$C$8 -> 47073.472 | E15: =B15 * C15 -> 8494.6684 | F15: =D15 - E15 -> 38578.804 | G15: =B15 - F15 -> 810888.03 | J15: =D15 + H15 + I15 -> 47073.472 | K15: =J15 / (1 + $K$6/12)^A15 -> 44067.83
A16: =+A15+1 -> 6 | B16: =G15 -> 810888.03 | C16: =$C$4 / 12 -> 0.01 | D16: =$C$8 -> 47073.472 | E16: =B16 * C16 -> 8108.8803 | F16: =D16 - E16 -> 38964.592 | G16: =B16 - F16 -> 771923.44 | J16: =D16 + H16 + I16 -> 47073.472 | K16: =J16 / (1 + $K$6/12)^A16 -> 43490.135
A17: =+A16+1 -> 7 | B17: =G16 -> 771923.44 | C17: =$C$4 / 12 -> 0.01 | D17: =$C$8 -> 47073.472 | E17: =B17 * C17 -> 7719.2344 | F17: =D17 - E17 -> 39354.238 | G17: =B17 - F17 -> 732569.2 | J17: =D17 + H17 + I17 -> 47073.472 | K17: =J17 / (1 + $K$6/12)^A17 -> 42920.012
A18: =+A17+1 -> 8 | B18: =G17 -> 732569.2 | C18: =$C$4 / 12 -> 0.01 | D18: =$C$8 -> 47073.472 | E18: =B18 * C18 -> 7325.692 | F18: =D18 - E18 -> 39747.78 | G18: =B18 - F18 -> 692821.42 | J18: =D18 + H18 + I18 -> 47073.472 | K18: =J18 / (1 + $K$6/12)^A18 -> 42357.364
A19: =+A18+1 -> 9 | B19: =G18 -> 692821.42 | C19: =$C$4 / 12 -> 0.01 | D19: =$C$8 -> 47073.472 | E19: =B19 * C19 -> 6928.2142 | F19: =D19 - E19 -> 40145.258 | G19: =B19 - F19 -> 652676.16 | J19: =D19 + H19 + I19 -> 47073.472 | K19: =J19 / (1 + $K$6/12)^A19 -> 41802.091
A20: =+A19+1 -> 10 | B20: =G19 -> 652676.16 | C20: =$C$4 / 12 -> 0.01 | D20: =$C$8 -> 47073.472 | E20: =B20 * C20 -> 6526.7616 | F20: =D20 - E20 -> 40546.711 | G20: =B20 - F20 -> 612129.45 | J20: =D20 + H20 + I20 -> 47073.472 | K20: =J20 / (1 + $K$6/12)^A20 -> 41254.098
A21: =+A20+1 -> 11 | B21: =G20 -> 612129.45 | C21: =$C$4 / 12 -> 0.01 | D21: =$C$8 -> 47073.472 | E21: =B21 * C21 -> 6121.2945 | F21: =D21 - E21 -> 40952.178 | G21: =B21 - F21 -> 571177.28 | J21: =D21 + H21 + I21 -> 47073.472 | K21: =J21 / (1 + $K$6/12)^A21 -> 40713.288
A22: =+A21+1 -> 12 | B22: =G21 -> 571177.28 | C22: =$C$4 / 12 -> 0.01 | D22: =$C$8 -> 47073.472 | E22: =B22 * C22 -> 5711.7728 | F22: =D22 - E22 -> 41361.699 | G22: =B22 - F22 -> 529815.58 | J22: =D22 + H22 + I22 -> 47073.472 | K22: =J22 / (1 + $K$6/12)^A22 -> 40179.568
A23: =+A22+1 -> 13 | B23: =G22 -> 529815.58 | C23: =$C$4 / 12 -> 0.01 | D23: =$C$8 -> 47073.472 | E23: =B23 * C23 -> 5298.1558 | F23: =D23 - E23 -> 41775.316 | G23: =B23 - F23 -> 488040.26 | I23: =C7 -> 10000 | J23: =D23 + H23 + I23 -> 57073.472 | K23: =J23 / (1 + $K$6/12)^A23 -> 48076.453
A24: =+A23+1 -> 14 | B24: =G23 -> 488040.26 | C24: =$C$4 / 12 -> 0.01 | D24: =$C$8 -> 47073.472 | E24: =B24 * C24 -> 4880.4026 | F24: =D24 - E24 -> 42193.07 | G24: =B24 - F24 -> 445847.19 | J24: =D24 + H24 + I24 -> 47073.472 | K24: =J24 / (1 + $K$6/12)^A24 -> 39133.027
A25: =+A24+1 -> 15 | B25: =G24 -> 445847.19 | C25: =$C$4 / 12 -> 0.01 | D25: =$C$8 -> 47073.472 | E25: =B25 * C25 -> 4458.4719 | F25: =D25 - E25 -> 42615 | G25: =B25 - F25 -> 403232.19 | J25: =D25 + H25 + I25 -> 47073.472 | K25: =J25 / (1 + $K$6/12)^A25 -> 38620.023
A26: =+A25+1 -> 16 | B26: =G25 -> 403232.19 | C26: =$C$4 / 12 -> 0.01 | D26: =$C$8 -> 47073.472 | E26: =B26 * C26 -> 4032.3219 | F26: =D26 - E26 -> 43041.15 | G26: =B26 - F26 -> 360191.04 | J26: =D26 + H26 + I26 -> 47073.472 | K26: =J26 / (1 + $K$6/12)^A26 -> 38113.744
A27: =+A26+1 -> 17 | B27: =G26 -> 360191.04 | C27: =$C$4 / 12 -> 0.01 | D27: =$C$8 -> 47073.472 | E27: =B27 * C27 -> 3601.9104 | F27: =D27 - E27 -> 43471.562 | G27: =B27 - F27 -> 316719.48 | J27: =D27 + H27 + I27 -> 47073.472 | K27: =J27 / (1 + $K$6/12)^A27 -> 37614.102
A28: =+A27+1 -> 18 | B28: =G27 -> 316719.48 | C28: =$C$4 / 12 -> 0.01 | D28: =$C$8 -> 47073.472 | E28: =B28 * C28 -> 3167.1948 | F28: =D28 - E28 -> 43906.277 | G28: =B28 - F28 -> 272813.2 | J28: =D28 + H28 + I28 -> 47073.472 | K28: =J28 / (1 + $K$6/12)^A28 -> 37121.01
A29: =+A28+1 -> 19 | B29: =G28 -> 272813.2 | C29: =$C$4 / 12 -> 0.01 | D29: =$C$8 -> 47073.472 | E29: =B29 * C29 -> 2728.132 | F29: =D29 - E29 -> 44345.34 | G29: =B29 - F29 -> 228467.86 | J29: =D29 + H29 + I29 -> 47073.472 | K29: =J29 / (1 + $K$6/12)^A29 -> 36634.382
A30: =+A29+1 -> 20 | B30: =G29 -> 228467.86 | C30: =$C$4 / 12 -> 0.01 | D30: =$C$8 -> 47073.472 | E30: =B30 * C30 -> 2284.6786 | F30: =D30 - E30 -> 44788.794 | G30: =B30 - F30 -> 183679.07 | J30: =D30 + H30 + I30 -> 47073.472 | K30: =J30 / (1 + $K$6/12)^A30 -> 36154.134
A31: =+A30+1 -> 21 | B31: =G30 -> 183679.07 | C31: =$C$4 / 12 -> 0.01 | D31: =$C$8 -> 47073.472 | E31: =B31 * C31 -> 1836.7907 | F31: =D31 - E31 -> 45236.682 | G31: =B31 - F31 -> 138442.39 | J31: =D31 + H31 + I31 -> 47073.472 | K31: =J31 / (1 + $K$6/12)^A31 -> 35680.181
A32: =+A31+1 -> 22 | B32: =G31 -> 138442.39 | C32: =$C$4 / 12 -> 0.01 | D32: =$C$8 -> 47073.472 | E32: =B32 * C32 -> 1384.4239 | F32: =D32 - E32 -> 45689.048 | G32: =B32 - F32 -> 92753.337 | J32: =D32 + H32 + I32 -> 47073.472 | K32: =J32 / (1 + $K$6/12)^A32 -> 35212.441
A33: =+A32+1 -> 23 | B33: =G32 -> 92753.337 | C33: =$C$4 / 12 -> 0.01 | D33: =$C$8 -> 47073.472 | E33: =B33 * C33 -> 927.53337 | F33: =D33 - E33 -> 46145.939 | G33: =B33 - F33 -> 46607.398 | J33: =D33 + H33 + I33 -> 47073.472 | K33: =J33 / (1 + $K$6/12)^A33 -> 34750.833
A34: =+A33+1 -> 24 | B34: =G33 -> 46607.398 | C34: =$C$4 / 12 -> 0.01 | D34: =$C$8 -> 47073.472 | E34: =B34 * C34 -> 466.07398 | F34: =D34 - E34 -> 46607.398 | G34: =B34 - F34 -> 2.3283064e-10 | J34: =D34 + H34 + I34 -> 47073.472 | K34: =J34 / (1 + $K$6/12)^A34 -> 34295.276

Sheet Modelo de Supervivencia
F1: Probabilidad de Incumplimiento calculada con Puntajes
A2: Tasa Efectiva = | B2: =+'Tabla de Amorticación'!K6 -> 0.1594004
H3: Severidad de la Pérdidad mediante la fórmula de las notas
A4: Modelo de Supervivencia
E5: Supuesto | G5: Supuesto
A6: Tiempo | B6: Tasa r | C6: EIt | D6: Factor de Descuento | E6: PI | F6: PSt-1 | G6: SP | H6: Reserva
A7: 1 | B7: =$B$2 / 12 -> 0.013283367 | C7: ='Tabla de Amorticación'!B11 -> 1000000 | D7: =1 / (1 + B7)^A7 -> 0.98689077 | E7: 0.25 | F7: =1 - E7 -> 0.75 | G7: 0.45 | H7: =(E7 * G7) * F7 * (C7 * D7) -> 83268.909
A8: =+A7+1 -> 2 | B8: =$B$2 / 12 -> 0.013283367 | C8: ='Tabla de Amorticación'!B12 -> 962926.53 | D8: =1 / (1 + B8)^A8 -> 0.97395339 | E8: 0.25 | F8: =F7 * (1 - E8) -> 0.5625 | G8: 0.45 | H8: =(E8 * G8) * F8 * (C8 * D8) -> 59348.039
A9: =+A8+1 -> 3 | B9: =$B$2 / 12 -> 0.013283367 | C9: ='Tabla de Amorticación'!B13 -> 925482.32 | D9: =1 / (1 + B9)^A9 -> 0.96118561 | E9: 0.25 | F9: =F8 * (1 - E9) -> 0.421875 | G9: 0.45 | H9: =(E9 * G9) * F9 * (C9 * D9) -> 42219.365
A10: =+A9+1 -> 4 | B10: =$B$2 / 12 -> 0.013283367 | C10: ='Tabla de Amorticación'!B14 -> 887663.67 | D10: =1 / (1 + B10)^A10 -> 0.9485852 | E10: 0.25 | F10: =F9 * (1 - E10) -> 0.31640625 | G10: 0.45 | H10: =(E10 * G10) * F10 * (C10 * D10) -> 29972.458
A11: =+A10+1 -> 5 | B11: =$B$2 / 12 -> 0.013283367 | C11: ='Tabla de Amorticación'!B15 -> 849466.84 | D11: =1 / (1 + B11)^A11 -> 0.93614998 | E11: 0.25 | F11: =F10 * (1 - E11) -> 0.23730469 | G11: 0.45 | H11: =(E11 * G11) * F11 * (C11 * D11) -> 21230.034
A12: =+A11+1 -> 6 | B12: =$B$2 / 12 -> 0.013283367 | C12: ='Tabla de Amorticación'!B16 -> 810888.03 | D12: =1 / (1 + B12)^A12 -> 0.92387777 | E12: 0.25 | F12: =F11 * (1 - E12) -> 0.17797852 | G12: 0.45 | H12: =(E12 * G12) * F12 * (C12 * D12) -> 15000.147
A13: =+A12+1 -> 7 | B13: =$B$2 / 12 -> 0.013283367 | C13: ='Tabla de Amorticación'!B17 -> 771923.44 | D13: =1 / (1 + B13)^A13 -> 0.91176644 | E13: 0.25 | F13: =F12 * (1 - E13) -> 0.13348389 | G13: 0.45 | H13: =(E13 * G13) * F13 * (C13 * D13) -> 10569.129
A14: =+A13+1 -> 8 | B14: =$B$2 / 12 -> 0.013283367 | C14: ='Tabla de Amorticación'!B18 -> 732569.2 | D14: =1 / (1 + B14)^A14 -> 0.89981388 | E14: 0.25 | F14: =F13 * (1 - E14) -> 0.10011292 | G14: 0.45 | H14: =(E14 * G14) * F14 * (C14 * D14) -> 7424.1028
A15: =+A14+1 -> 9 | B15: =$B$2 / 12 -> 0.013283367 | C15: ='Tabla de Amorticación'!B19 -> 692821.42 | D15: =1 / (1 + B15)^A15 -> 0.88801801 | E15: 0.25 | F15: =F14 * (1 - E15) -> 0.075084686 | G15: 0.45 | H15: =(E15 * G15) * F15 * (C15 * D15) -> 5196.9313
A16: =+A15+1 -> 10 | B16: =$B$2 / 12 -> 0.013283367 | C16: ='Tabla de Amorticación'!B20 -> 652676.16 | D16: =1 / (1 + B16)^A16 -> 0.87637678 | E16: 0.25 | F16: =F15 * (1 - E16) -> 0.056313515 | G16: 0.45 | H16: =(E16 * G16) * F16 * (C16 * D16) -> 3623.7128
A17: =+A16+1 -> 11 | B17: =$B$2 / 12 -> 0.013283367 | C17: ='Tabla de Amorticación'!B21 -> 612129.45 | D17: =1 / (1 + B17)^A17 -> 0.86488815 | E17: 0.25 | F17: =F16 * (1 - E17) -> 0.042235136 | G17: 0.45 | H17: =(E17 * G17) * F17 * (C17 * D17) -> 2515.5308
A18: =+A17+1 -> 12 | B18: =$B$2 / 12 -> 0.013283367 | C18: ='Tabla de Amorticación'!B22 -> 571177.28 | D18: =1 / (1 + B18)^A18 -> 0.85355013 | E18: 0.25 | F18: =F17 * (1 - E18) -> 0.031676352 | G18: 0.45 | H18: =(E18 * G18) * F18 * (C18 * D18) -> 1737.3513
A19: =+A18+1 -> 13 | B19: =$B$2 / 12 -> 0.013283367 | C19: ='Tabla de Amorticación'!B23 -> 529815.58 | D19: =1 / (1 + B19)^A19 -> 0.84236075 | E19: 0.25 | F19: =F18 * (1 - E19) -> 0.023757264 | G19: 0.45 | H19: =(E19 * G19) * F19 * (C19 * D19) -> 1192.8114
... A30: =+A29+1 -> 24 | B30: =$B$2 / 12 -> 0.013283367 | C30: ='Tabla de Amorticación'!B34 -> 46607.398 | D30: =1 / (1 + B30)^A30 -> 0.72854783 | E30: 0.25 | F30: =F29 * (1 - E30) -> 0.0010033913 | G30: 0.45 | H30: =(E30 * G30) * F30 * (C30 * D30) -> 3.8329731
F32: Reserva lifetime = | H32: =SUM(H7:H30) -> 285667.39
F35: Reserva 12m = | H35: =SUM(H7:H18) -> 282105.71
