Workbook

Sheet INTEGRANTES
B3: Arana Francisco Sandra - 318225146
B4: Mendieta Lopez David - 317231186
B5: David Hernández Bautista - 317356823

Sheet Crédito Pagos Constantes
A1: Tabla de Amortización del Crédito con Pagos Iguales o Constantes
A3: Línea de Crédito | B3: 1500000 | D3: Línea de Crédito Modificada | E3: =B3-E4 -> 1316489.4
A4: Pago Final en el mes 48 del Crédito | B4: =+B3*0.25 -> 375000 | D4: Valor Presente del pago final | E4: =B4*(1+B5/12)^(-B6) -> 183510.64
A5: Tasa del Crédito (Anual) | B5: 0.18
A6: Tiempo (n) | B6: 48 | C6: meses
A7: Tasa Comisión por Apertura | B7: 0.03 | J7: Tasa Efectiva | K7: 0.20502675
A8: Pago de Seguro (Anual) | B8: 10000
A9: Pago Mensual = | B9: =-PMT(B5/12,B6,E3,0,0) -> 38671.875 | K9: Flujos Totales
K10: =+SUM(K12:K59) -> 1500000
A11: Tiempo | B11: SI Inicio | C11: Tasa | D11: Pago = Cap + Interese | E11: Interese | F11: Pago a Capital | G11: SI Final | H11: Comisión por Apertura | I11: Seguro de Vida | J11: Pago Final | K11: Flujos a VP
A12: 1 | B12: =B3 -> 1500000 | C12: =$B$5/12 -> 0.015 | D12: =$B$9 -> 38671.875 | E12: =C12*B12 -> 22500 | F12: =D12-E12 -> 16171.875 | G12: =B12-F12 -> 1483828.1 | H12: =B7*B3 -> 45000 | I12: =B8 -> 10000 | J12: =D12+H12+I12 -> 93671.875 | K12: =J12/(1+$K$7/12)^A12 -> 92098.323
A13: =+A12+1 -> 2 | B13: =G12 -> 1483828.1 | C13: =$B$5/12 -> 0.015 | D13: =$B$9 -> 38671.875 | E13: =C13*B13 -> 22257.422 | F13: =D13-E13 -> 16414.453 | G13: =B13-F13 -> 1467413.7 | J13: =D13+H13+I13 -> 38671.875 | K13: =J13/(1+$K$7/12)^A13 -> 37383.525
A14: =+A13+1 -> 3 | B14: =G13 -> 1467413.7 | C14: =$B$5/12 -> 0.015 | D14: =$B$9 -> 38671.875 | E14: =C14*B14 -> 22011.205 | F14: =D14-E14 -> 16660.669 | G14: =B14-F14 -> 1450753 | J14: =D14+H14+I14 -> 38671.875 | K14: =J14/(1+$K$7/12)^A14 -> 36755.536
A15: =+A14+1 -> 4 | B15: =G14 -> 1450753 | C15: =$B$5/12 -> 0.015 | D15: =$B$9 -> 38671.875 | E15: =C15*B15 -> 21761.295 | F15: =D15-E15 -> 16910.58 | G15: =B15-F15 -> 1433842.4 | J15: =D15+H15+I15 -> 38671.875 | K15: =J15/(1+$K$7/12)^A15 -> 36138.096
A16: =+A15+1 -> 5 | B16: =G15 -> 1433842.4 | C16: =$B$5/12 -> 0.015 | D16: =$B$9 -> 38671.875 | E16: =C16*B16 -> 21507.636 | F16: =D16-E16 -> 17164.238 | G16: =B16-F16 -> 1416678.2 | J16: =D16+H16+I16 -> 38671.875 | K16: =J16/(1+$K$7/12)^A16 -> 35531.028
A17: =+A16+1 -> 6 | B17: =G16 -> 1416678.2 | C17: =$B$5/12 -> 0.015 | D17: =$B$9 -> 38671.875 | E17: =C17*B17 -> 21250.173 | F17: =D17-E17 -> 17421.702 | G17: =B17-F17 -> 1399256.5 | J17: =D17+H17+I17 -> 38671.875 | K17: =J17/(1+$K$7/12)^A17 -> 34934.159
A18: =+A17+1 -> 7 | B18: =G17 -> 1399256.5 | C18: =$B$5/12 -> 0.015 | D18: =$B$9 -> 38671.875 | E18: =C18*B18 -> 20988.847 | F18: =D18-E18 -> 17683.027 | G18: =B18-F18 -> 1381573.5 | J18: =D18+H18+I18 -> 38671.875 | K18: =J18/(1+$K$7/12)^A18 -> 34347.315
A19: =+A18+1 -> 8 | B19: =G18 -> 1381573.5 | C19: =$B$5/12 -> 0.015 | D19: =$B$9 -> 38671.875 | E19: =C19*B19 -> 20723.602 | F19: =D19-E19 -> 17948.273 | G19: =B19-F19 -> 1363625.2 | J19: =D19+H19+I19 -> 38671.875 | K19: =J19/(1+$K$7/12)^A19 -> 33770.33
A20: =+A19+1 -> 9 | B20: =G19 -> 1363625.2 | C20: =$B$5/12 -> 0.015 | D20: =$B$9 -> 38671.875 | E20: =C20*B20 -> 20454.378 | F20: =D20-E20 -> 18217.497 | G20: =B20-F20 -> 1345407.7 | J20: =D20+H20+I20 -> 38671.875 | K20: =J20/(1+$K$7/12)^A20 -> 33203.038
A21: =+A20+1 -> 10 | B21: =G20 -> 1345407.7 | C21: =$B$5/12 -> 0.015 | D21: =$B$9 -> 38671.875 | E21: =C21*B21 -> 20181.115 | F21: =D21-E21 -> 18490.759 | G21: =B21-F21 -> 1326916.9 | J21: =D21+H21+I21 -> 38671.875 | K21: =J21/(1+$K$7/12)^A21 -> 32645.275
A22: =+A21+1 -> 11 | B22: =G21 -> 1326916.9 | C22: =$B$5/12 -> 0.015 | D22: =$B$9 -> 38671.875 | E22: =C22*B22 -> 19903.754 | F22: =D22-E22 -> 18768.121 | G22: =B22-F22 -> 1308148.8 | J22: =D22+H22+I22 -> 38671.875 | K22: =J22/(1+$K$7/12)^A22 -> 32096.882
A23: =+A22+1 -> 12 | B23: =G22 -> 1308148.8 | C23: =$B$5/12 -> 0.015 | D23: =$B$9 -> 38671.875 | E23: =C23*B23 -> 19622.232 | F23: =D23-E23 -> 19049.642 | G23: =B23-F23 -> 1289099.2 | J23: =D23+H23+I23 -> 38671.875 | K23: =J23/(1+$K$7/12)^A23 -> 31557.7
A24: =+A23+1 -> 13 | B24: =G23 -> 1289099.2 | C24: =$B$5/12 -> 0.015 | D24: =$B$9 -> 38671.875 | E24: =C24*B24 -> 19336.487 | F24: =D24-E24 -> 19335.387 | G24: =B24-F24 -> 1269763.8 | I24: =I12 -> 10000 | J24: =D24+H24+I24 -> 48671.875 | K24: =J24/(1+$K$7/12)^A24 -> 39050.87
A25: =+A24+1 -> 14 | B25: =G24 -> 1269763.8 | C25: =$B$5/12 -> 0.015 | D25: =$B$9 -> 38671.875 | E25: =C25*B25 -> 19046.457 | F25: =D25-E25 -> 19625.418 | G25: =B25-F25 -> 1250138.4 | J25: =D25+H25+I25 -> 38671.875 | K25: =J25/(1+$K$7/12)^A25 -> 30506.359
A26: =+A25+1 -> 15 | B26: =G25 -> 1250138.4 | C26: =$B$5/12 -> 0.015 | D26: =$B$9 -> 38671.875 | E26: =C26*B26 -> 18752.075 | F26: =D26-E26 -> 19919.799 | G26: =B26-F26 -> 1230218.6 | J26: =D26+H26+I26 -> 38671.875 | K26: =J26/(1+$K$7/12)^A26 -> 29993.896
A27: =+A26+1 -> 16 | B27: =G26 -> 1230218.6 | C27: =$B$5/12 -> 0.015 | D27: =$B$9 -> 38671.875 | E27: =C27*B27 -> 18453.278 | F27: =D27-E27 -> 20218.596 | G27: =B27-F27 -> 1210000 | J27: =D27+H27+I27 -> 38671.875 | K27: =J27/(1+$K$7/12)^A27 -> 29490.042
A28: =+A27+1 -> 17 | B28: =G27 -> 1210000 | C28: =$B$5/12 -> 0.015 | D28: =$B$9 -> 38671.875 | E28: =C28*B28 -> 18149.999 | F28: =D28-E28 -> 20521.875 | G28: =B28-F28 -> 1189478.1 | J28: =D28+H28+I28 -> 38671.875 | K28: =J28/(1+$K$7/12)^A28 -> 28994.652
A29: =+A28+1 -> 18 | B29: =G28 -> 1189478.1 | C29: =$B$5/12 -> 0.015 | D29: =$B$9 -> 38671.875 | E29: =C29*B29 -> 17842.171 | F29: =D29-E29 -> 20829.703 | G29: =B29-F29 -> 1168648.4 | J29: =D29+H29+I29 -> 38671.875 | K29: =J29/(1+$K$7/12)^A29 -> 28507.584
A30: =+A29+1 -> 19 | B30: =G29 -> 1168648.4 | C30: =$B$5/12 -> 0.015 | D30: =$B$9 -> 38671.875 | E30: =C30*B30 -> 17529.726 | F30: =D30-E30 -> 21142.149 | G30: =B30-F30 -> 1147506.2 | J30: =D30+H30+I30 -> 38671.875 | K30: =J30/(1+$K$7/12)^A30 -> 28028.698
A31: =+A30+1 -> 20 | B31: =G30 -> 1147506.2 | C31: =$B$5/12 -> 0.015 | D31: =$B$9 -> 38671.875 | E31: =C31*B31 -> 17212.594 | F31: =D31-E31 -> 21459.281 | G31: =B31-F31 -> 1126047 | J31: =D31+H31+I31 -> 38671.875 | K31: =J31/(1+$K$7/12)^A31 -> 27557.856
A32: =+A31+1 -> 21 | B32: =G31 -> 1126047 | C32: =$B$5/12 -> 0.015 | D32: =$B$9 -> 38671.875 | E32: =C32*B32 -> 16890.704 | F32: =D32-E32 -> 21781.17 | G32: =B32-F32 -> 1104265.8 | J32: =D32+H32+I32 -> 38671.875 | K32: =J32/(1+$K$7/12)^A32 -> 27094.924
A33: =+A32+1 -> 22 | B33: =G32 -> 1104265.8 | C33: =$B$5/12 -> 0.015 | D33: =$B$9 -> 38671.875 | E33: =C33*B33 -> 16563.987 | F33: =D33-E33 -> 22107.888 | G33: =B33-F33 -> 1082157.9 | J33: =D33+H33+I33 -> 38671.875 | K33: =J33/(1+$K$7/12)^A33 -> 26639.769
A34: =+A33+1 -> 23 | B34: =G33 -> 1082157.9 | C34: =$B$5/12 -> 0.015 | D34: =$B$9 -> 38671.875 | E34: =C34*B34 -> 16232.368 | F34: =D34-E34 -> 22439.506 | G34: =B34-F34 -> 1059718.4 | J34: =D34+H34+I34 -> 38671.875 | K34: =J34/(1+$K$7/12)^A34 -> 26192.259
A35: =+A34+1 -> 24 | B35: =G34 -> 1059718.4 | C35: =$B$5/12 -> 0.015 | D35: =$B$9 -> 38671.875 | E35: =C35*B35 -> 15895.776 | F35: =D35-E35 -> 22776.099 | G35: =B35-F35 -> 1036942.3 | J35: =D35+H35+I35 -> 38671.875 | K35: =J35/(1+$K$7/12)^A35 -> 25752.268
A36: =+A35+1 -> 25 | B36: =G35 -> 1036942.3 | C36: =$B$5/12 -> 0.015 | D36: =$B$9 -> 38671.875 | E36: =C36*B36 -> 15554.134 | F36: =D36-E36 -> 23117.74 | G36: =B36-F36 -> 1013824.6 | I36: =I24 -> 10000 | J36: =D36+H36+I36 -> 48671.875 | K36: =J36/(1+$K$7/12)^A36 -> 31866.975
A37: =+A36+1 -> 26 | B37: =G36 -> 1013824.6 | C37: =$B$5/12 -> 0.015 | D37: =$B$9 -> 38671.875 | E37: =C37*B37 -> 15207.368 | F37: =D37-E37 -> 23464.506 | G37: =B37-F37 -> 990360.05 | J37: =D37+H37+I37 -> 38671.875 | K37: =J37/(1+$K$7/12)^A37 -> 24894.333
A38: =+A37+1 -> 27 | B38: =G37 -> 990360.05 | C38: =$B$5/12 -> 0.015 | D38: =$B$9 -> 38671.875 | E38: =C38*B38 -> 14855.401 | F38: =D38-E38 -> 23816.474 | G38: =B38-F38 -> 966543.57 | J38: =D38+H38+I38 -> 38671.875 | K38: =J38/(1+$K$7/12)^A38 -> 24476.144
A39: =+A38+1 -> 28 | B39: =G38 -> 966543.57 | C39: =$B$5/12 -> 0.015 | D39: =$B$9 -> 38671.875 | E39: =C39*B39 -> 14498.154 | F39: =D39-E39 -> 24173.721 | G39: =B39-F39 -> 942369.85 | J39: =D39+H39+I39 -> 38671.875 | K39: =J39/(1+$K$7/12)^A39 -> 24064.981
A40: =+A39+1 -> 29 | B40: =G39 -> 942369.85 | C40: =$B$5/12 -> 0.015 | D40: =$B$9 -> 38671.875 | E40: =C40*B40 -> 14135.548 | F40: =D40-E40 -> 24536.327 | G40: =B40-F40 -> 917833.53 | J40: =D40+H40+I40 -> 38671.875 | K40: =J40/(1+$K$7/12)^A40 -> 23660.724
A41: =+A40+1 -> 30 | B41: =G40 -> 917833.53 | C41: =$B$5/12 -> 0.015 | D41: =$B$9 -> 38671.875 | E41: =C41*B41 -> 13767.503 | F41: =D41-E41 -> 24904.372 | G41: =B41-F41 -> 892929.15 | J41: =D41+H41+I41 -> 38671.875 | K41: =J41/(1+$K$7/12)^A41 -> 23263.258
A42: =+A41+1 -> 31 | B42: =G41 -> 892929.15 | C42: =$B$5/12 -> 0.015 | D42: =$B$9 -> 38671.875 | E42: =C42*B42 -> 13393.937 | F42: =D42-E42 -> 25277.937 | G42: =B42-F42 -> 867651.22 | J42: =D42+H42+I42 -> 38671.875 | K42: =J42/(1+$K$7/12)^A42 -> 22872.469
A43: =+A42+1 -> 32 | B43: =G42 -> 867651.22 | C43: =$B$5/12 -> 0.015 | D43: =$B$9 -> 38671.875 | E43: =C43*B43 -> 13014.768 | F43: =D43-E43 -> 25657.106 | G43: =B43-F43 -> 841994.11 | J43: =D43+H43+I43 -> 38671.875 | K43: =J43/(1+$K$7/12)^A43 -> 22488.245
A44: =+A43+1 -> 33 | B44: =G43 -> 841994.11 | C44: =$B$5/12 -> 0.015 | D44: =$B$9 -> 38671.875 | E44: =C44*B44 -> 12629.912 | F44: =D44-E44 -> 26041.963 | G44: =B44-F44 -> 815952.15 | J44: =D44+H44+I44 -> 38671.875 | K44: =J44/(1+$K$7/12)^A44 -> 22110.475
A45: =+A44+1 -> 34 | B45: =G44 -> 815952.15 | C45: =$B$5/12 -> 0.015 | D45: =$B$9 -> 38671.875 | E45: =C45*B45 -> 12239.282 | F45: =D45-E45 -> 26432.592 | G45: =B45-F45 -> 789519.56 | J45: =D45+H45+I45 -> 38671.875 | K45: =J45/(1+$K$7/12)^A45 -> 21739.051
A46: =+A45+1 -> 35 | B46: =G45 -> 789519.56 | C46: =$B$5/12 -> 0.015 | D46: =$B$9 -> 38671.875 | E46: =C46*B46 -> 11842.793 | F46: =D46-E46 -> 26829.081 | G46: =B46-F46 -> 762690.47 | J46: =D46+H46+I46 -> 38671.875 | K46: =J46/(1+$K$7/12)^A46 -> 21373.866
A47: =+A46+1 -> 36 | B47: =G46 -> 762690.47 | C47: =$B$5/12 -> 0.015 | D47: =$B$9 -> 38671.875 | E47: =C47*B47 -> 11440.357 | F47: =D47-E47 -> 27231.517 | G47: =B47-F47 -> 735458.96 | J47: =D47+H47+I47 -> 38671.875 | K47: =J47/(1+$K$7/12)^A47 -> 21014.816
A48: =+A47+1 -> 37 | B48: =G47 -> 735458.96 | C48: =$B$5/12 -> 0.015 | D48: =$B$9 -> 38671.875 | E48: =C48*B48 -> 11031.884 | F48: =D48-E48 -> 27639.99 | G48: =B48-F48 -> 707818.97 | I48: =I36 -> 10000 | J48: =D48+H48+I48 -> 48671.875 | K48: =J48/(1+$K$7/12)^A48 -> 26004.647
A49: =+A48+1 -> 38 | B49: =G48 -> 707818.97 | C49: =$B$5/12 -> 0.015 | D49: =$B$9 -> 38671.875 | E49: =C49*B49 -> 10617.284 | F49: =D49-E49 -> 28054.59 | G49: =B49-F49 -> 679764.38 | J49: =D49+H49+I49 -> 38671.875 | K49: =J49/(1+$K$7/12)^A49 -> 20314.71
A50: =+A49+1 -> 39 | B50: =G49 -> 679764.38 | C50: =$B$5/12 -> 0.015 | D50: =$B$9 -> 38671.875 | E50: =C50*B50 -> 10196.466 | F50: =D50-E50 -> 28475.409 | G50: =B50-F50 -> 651288.97 | J50: =D50+H50+I50 -> 38671.875 | K50: =J50/(1+$K$7/12)^A50 -> 19973.452
A51: =+A50+1 -> 40 | B51: =G50 -> 651288.97 | C51: =$B$5/12 -> 0.015 | D51: =$B$9 -> 38671.875 | E51: =C51*B51 -> 9769.3345 | F51: =D51-E51 -> 28902.54 | G51: =B51-F51 -> 622386.43 | J51: =D51+H51+I51 -> 38671.875 | K51: =J51/(1+$K$7/12)^A51 -> 19637.927
A52: =+A51+1 -> 41 | B52: =G51 -> 622386.43 | C52: =$B$5/12 -> 0.015 | D52: =$B$9 -> 38671.875 | E52: =C52*B52 -> 9335.7964 | F52: =D52-E52 -> 29336.078 | G52: =B52-F52 -> 593050.35 | J52: =D52+H52+I52 -> 38671.875 | K52: =J52/(1+$K$7/12)^A52 -> 19308.038
A53: =+A52+1 -> 42 | B53: =G52 -> 593050.35 | C53: =$B$5/12 -> 0.015 | D53: =$B$9 -> 38671.875 | E53: =C53*B53 -> 8895.7552 | F53: =D53-E53 -> 29776.119 | G53: =B53-F53 -> 563274.23 | J53: =D53+H53+I53 -> 38671.875 | K53: =J53/(1+$K$7/12)^A53 -> 18983.691
A54: =+A53+1 -> 43 | B54: =G53 -> 563274.23 | C54: =$B$5/12 -> 0.015 | D54: =$B$9 -> 38671.875 | E54: =C54*B54 -> 8449.1134 | F54: =D54-E54 -> 30222.761 | G54: =B54-F54 -> 533051.47 | J54: =D54+H54+I54 -> 38671.875 | K54: =J54/(1+$K$7/12)^A54 -> 18664.793
A55: =+A54+1 -> 44 | B55: =G54 -> 533051.47 | C55: =$B$5/12 -> 0.015 | D55: =$B$9 -> 38671.875 | E55: =C55*B55 -> 7995.772 | F55: =D55-E55 -> 30676.103 | G55: =B55-F55 -> 502375.37 | J55: =D55+H55+I55 -> 38671.875 | K55: =J55/(1+$K$7/12)^A55 -> 18351.251
A56: =+A55+1 -> 45 | B56: =G55 -> 502375.37 | C56: =$B$5/12 -> 0.015 | D56: =$B$9 -> 38671.875 | E56: =C56*B56 -> 7535.6305 | F56: =D56-E56 -> 31136.244 | G56: =B56-F56 -> 471239.12 | J56: =D56+H56+I56 -> 38671.875 | K56: =J56/(1+$K$7/12)^A56 -> 18042.977
A57: =+A56+1 -> 46 | B57: =G56 -> 471239.12 | C57: =$B$5/12 -> 0.015 | D57: =$B$9 -> 38671.875 | E57: =C57*B57 -> 7068.5868 | F57: =D57-E57 -> 31603.288 | G57: =B57-F57 -> 439635.83 | J57: =D57+H57+I57 -> 38671.875 | K57: =J57/(1+$K$7/12)^A57 -> 17739.881
A58: =+A57+1 -> 47 | B58: =G57 -> 439635.83 | C58: =$B$5/12 -> 0.015 | D58: =$B$9 -> 38671.875 | E58: =C58*B58 -> 6594.5375 | F58: =D58-E58 -> 32077.337 | G58: =B58-F58 -> 407558.5 | J58: =D58+H58+I58 -> 38671.875 | K58: =J58/(1+$K$7/12)^A58 -> 17441.877
A59: =+A58+1 -> 48 | B59: =G58 -> 407558.5 | C59: =$B$5/12 -> 0.015 | D59: =$B$9+B4 -> 413671.87 | E59: =C59*B59 -> 6113.3775 | F59: =D59-E59 -> 407558.5 | G59: =B59-F59 -> 2.0954758e-09 | J59: =D59+H59+I59 -> 413671.87 | K59: =J59/(1+$K$7/12)^A59 -> 183441.04

Sheet M. Supervivencia Pago Const.
A1: Etapa del Crédito = | B1: 1 | F1: Probabilidad de Incumplimiento calculada con Puntajes
A2: Tasa Efectiva = | B2: =+'Crédito Pagos Constantes'!K7 -> 0.20502675
H3: Severidad de la Pérdidad mediante la fórmula de las notas
A4: Modelo de Supervivencia
E5: Supuesto | G5: Supuesto
A6: Tiempo | B6: Tasa r | C6: EIt | D6: Factor de Descuento | E6: PI | F6: PSt-1 | G6: SP | H6: Reserva
A7: 1 | B7: =$B$2 /12 -> 0.017085562 | C7: ='Crédito Pagos Constantes'!B12 -> 1500000 | D7: =1/(1+B7)^A7 -> 0.98320145 | E7: 0.05 | F7: =1-E7 -> 0.95 | G7: 0.45 | H7: =E7*F7*G7*D7*C7 -> 31523.896
A8: =+A7+1 -> 2 | B8: =$B$2 /12 -> 0.017085562 | C8: ='Crédito Pagos Constantes'!B13 -> 1483828.1 | D8: =1/(1+B8)^A8 -> 0.96668509 | E8: 0.05 | F8: =F7*(1-E8) -> 0.9025 | G8: 0.45 | H8: =E8*F8*G8*D8*C8 -> 29127.174
A9: =+A8+1 -> 3 | B9: =$B$2 /12 -> 0.017085562 | C9: ='Crédito Pagos Constantes'!B14 -> 1467413.7 | D9: =1/(1+B9)^A9 -> 0.95044618 | E9: 0.05 | F9: =F8*(1-E9) -> 0.857375 | G9: 0.45 | H9: =E9*F9*G9*D9*C9 -> 26905.027
A10: =+A9+1 -> 4 | B10: =$B$2 /12 -> 0.017085562 | C10: ='Crédito Pagos Constantes'!B15 -> 1450753 | D10: =1/(1+B10)^A10 -> 0.93448007 | E10: 0.05 | F10: =F9*(1-E10) -> 0.81450625 | G10: 0.45 | H10: =E10*F10*G10*D10*C10 -> 24845.083
A11: =+A10+1 -> 5 | B11: =$B$2 /12 -> 0.017085562 | C11: ='Crédito Pagos Constantes'!B16 -> 1433842.4 | D11: =1/(1+B11)^A11 -> 0.91878216 | E11: 0.05 | F11: =F10*(1-E11) -> 0.77378094 | G11: 0.45 | H11: =E11*F11*G11*D11*C11 -> 22935.833
A12: =+A11+1 -> 6 | B12: =$B$2 /12 -> 0.017085562 | C12: ='Crédito Pagos Constantes'!B17 -> 1416678.2 | D12: =1/(1+B12)^A12 -> 0.90334795 | E12: 0.05 | F12: =F11*(1-E12) -> 0.73509189 | G12: 0.45 | H12: =E12*F12*G12*D12*C12 -> 21166.567
A13: =+A12+1 -> 7 | B13: =$B$2 /12 -> 0.017085562 | C13: ='Crédito Pagos Constantes'!B18 -> 1399256.5 | D13: =1/(1+B13)^A13 -> 0.88817301 | E13: 0.05 | F13: =F12*(1-E13) -> 0.6983373 | G13: 0.45 | H13: =E13*F13*G13*D13*C13 -> 19527.321
A14: =+A13+1 -> 8 | B14: =$B$2 /12 -> 0.017085562 | C14: ='Crédito Pagos Constantes'!B19 -> 1381573.5 | D14: =1/(1+B14)^A14 -> 0.87325299 | E14: 0.05 | F14: =F13*(1-E14) -> 0.66342043 | G14: 0.45 | H14: =E14*F14*G14*D14*C14 -> 18008.827
A15: =+A14+1 -> 9 | B15: =$B$2 /12 -> 0.017085562 | C15: ='Crédito Pagos Constantes'!B20 -> 1363625.2 | D15: =1/(1+B15)^A15 -> 0.85858361 | E15: 0.05 | F15: =F14*(1-E15) -> 0.63024941 | G15: 0.45 | H15: =E15*F15*G15*D15*C15 -> 16602.465
A16: =+A15+1 -> 10 | B16: =$B$2 /12 -> 0.017085562 | C16: ='Crédito Pagos Constantes'!B21 -> 1345407.7 | D16: =1/(1+B16)^A16 -> 0.84416065 | E16: 0.05 | F16: =F15*(1-E16) -> 0.59873694 | G16: 0.45 | H16: =E16*F16*G16*D16*C16 -> 15300.217
A17: =+A16+1 -> 11 | B17: =$B$2 /12 -> 0.017085562 | C17: ='Crédito Pagos Constantes'!B22 -> 1326916.9 | D17: =1/(1+B17)^A17 -> 0.82997998 | E17: 0.05 | F17: =F16*(1-E17) -> 0.56880009 | G17: 0.45 | H17: =E17*F17*G17*D17*C17 -> 14094.625
A18: =+A17+1 -> 12 | B18: =$B$2 /12 -> 0.017085562 | C18: ='Crédito Pagos Constantes'!B23 -> 1308148.8 | D18: =1/(1+B18)^A18 -> 0.81603752 | E18: 0.05 | F18: =F17*(1-E18) -> 0.54036009 | G18: 0.45 | H18: =E18*F18*G18*D18*C18 -> 12978.756
A19: =+A18+1 -> 13 | B19: =$B$2 /12 -> 0.017085562 | C19: ='Crédito Pagos Constantes'!B24 -> 1289099.2 | D19: =1/(1+B19)^A19 -> 0.80232927 | E19: 0.05 | F19: =F18*(1-E19) -> 0.51334208 | G19: 0.45 | H19: =E19*F19*G19*D19*C19 -> 11946.161
... A54: =+A53+1 -> 48 | B54: =$B$2 /12 -> 0.017085562 | C54: ='Crédito Pagos Constantes'!B59 -> 407558.5 | D54: =1/(1+B54)^A54 -> 0.44344575 | E54: 0.05 | F54: =F53*(1-E54) -> 0.08525759 | G54: 0.45 | H54: =E54*F54*G54*D54*C54 -> 346.69376
F56: Reserva lifetime = | H56: =SUM(H7:H54) -> 387927.17
F59: Reserva 12m = | H59: =SUM(H7:H18) -> 253015.79

Sheet Crédito Pagos Decrecientes
A1: Tabla de Amortización del Crédito con Pagos Decrecientes
A3: Línea de Crédito | B3: 1200000
A4: Tasa del Crédito (Anual) | B4: 0.15
A5: Tiempo (n) | B5: 36 | C5: meses
A6: Tasa Comisión por Apertura | B6: 0.01 | J6: Tasa Efectiva | K6: 0.17704985
A7: Pagar Seguro (Anual) | B7: 12000
A8: Pago a Capital Mensual | B8: =B3/B5 -> 33333.333 | K8: Flujos Totales
K9: =+SUM(K11:K46) -> 1200000
A10: Tiempo | B10: SI Inicio | C10: Tasa | D10: Pago = Cap + Intereses | E10: Interes | F10: Pago a Capital | G10: SI Final | H10: Comisión por Apertura | I10: Seguro de Vida | J10: Pago Final | K10: Flujos a VP
A11: 1 | B11: =B3 -> 1200000 | C11: =$B$4/12 -> 0.0125 | D11: =F11+E11 -> 48333.333 | E11: =B11*C11 -> 15000 | F11: =$B$8 -> 33333.333 | G11: =B11-F11 -> 1166666.7 | H11: =B11*$B$6 -> 12000 | I11: =B7 -> 12000 | J11: =D11+H11+I11 -> 72333.333 | K11: =J11/(1+$K$6/12)^A11 -> 71281.633
A12: =+A11+1 -> 2 | B12: =G11 -> 1166666.7 | C12: =$B$4/12 -> 0.0125 | D12: =F12+E12 -> 47916.667 | E12: =B12*C12 -> 14583.333 | F12: =$B$8 -> 33333.333 | G12: =B12-F12 -> 1133333.3 | J12: =D12+H12+I12 -> 47916.667 | K12: =J12/(1+$K$6/12)^A12 -> 46533.415
A13: =+A12+1 -> 3 | B13: =G12 -> 1133333.3 | C13: =$B$4/12 -> 0.0125 | D13: =F13+E13 -> 47500 | E13: =B13*C13 -> 14166.667 | F13: =$B$8 -> 33333.333 | G13: =B13-F13 -> 1100000 | J13: =D13+H13+I13 -> 47500 | K13: =J13/(1+$K$6/12)^A13 -> 45458.081
A14: =+A13+1 -> 4 | B14: =G13 -> 1100000 | C14: =$B$4/12 -> 0.0125 | D14: =F14+E14 -> 47083.333 | E14: =B14*C14 -> 13750 | F14: =$B$8 -> 33333.333 | G14: =B14-F14 -> 1066666.7 | J14: =D14+H14+I14 -> 47083.333 | K14: =J14/(1+$K$6/12)^A14 -> 44404.18
A15: =+A14+1 -> 5 | B15: =G14 -> 1066666.7 | C15: =$B$4/12 -> 0.0125 | D15: =F15+E15 -> 46666.667 | E15: =B15*C15 -> 13333.333 | F15: =$B$8 -> 33333.333 | G15: =B15-F15 -> 1033333.3 | J15: =D15+H15+I15 -> 46666.667 | K15: =J15/(1+$K$6/12)^A15 -> 43371.315
A16: =+A15+1 -> 6 | B16: =G15 -> 1033333.3 | C16: =$B$4/12 -> 0.0125 | D16: =F16+E16 -> 46250 | E16: =B16*C16 -> 12916.667 | F16: =$B$8 -> 33333.333 | G16: =B16-F16 -> 1000000 | J16: =D16+H16+I16 -> 46250 | K16: =J16/(1+$K$6/12)^A16 -> 42359.099
A17: =+A16+1 -> 7 | B17: =G16 -> 1000000 | C17: =$B$4/12 -> 0.0125 | D17: =F17+E17 -> 45833.333 | E17: =B17*C17 -> 12500 | F17: =$B$8 -> 33333.333 | G17: =B17-F17 -> 966666.67 | J17: =D17+H17+I17 -> 45833.333 | K17: =J17/(1+$K$6/12)^A17 -> 41367.148
A18: =+A17+1 -> 8 | B18: =G17 -> 966666.67 | C18: =$B$4/12 -> 0.0125 | D18: =F18+E18 -> 45416.667 | E18: =B18*C18 -> 12083.333 | F18: =$B$8 -> 33333.333 | G18: =B18-F18 -> 933333.33 | J18: =D18+H18+I18 -> 45416.667 | K18: =J18/(1+$K$6/12)^A18 -> 40395.088
A19: =+A18+1 -> 9 | B19: =G18 -> 933333.33 | C19: =$B$4/12 -> 0.0125 | D19: =F19+E19 -> 45000 | E19: =B19*C19 -> 11666.667 | F19: =$B$8 -> 33333.333 | G19: =B19-F19 -> 900000 | J19: =D19+H19+I19 -> 45000 | K19: =J19/(1+$K$6/12)^A19 -> 39442.549
A20: =+A19+1 -> 10 | B20: =G19 -> 900000 | C20: =$B$4/12 -> 0.0125 | D20: =F20+E20 -> 44583.333 | E20: =B20*C20 -> 11250 | F20: =$B$8 -> 33333.333 | G20: =B20-F20 -> 866666.67 | J20: =D20+H20+I20 -> 44583.333 | K20: =J20/(1+$K$6/12)^A20 -> 38509.17
A21: =+A20+1 -> 11 | B21: =G20 -> 866666.67 | C21: =$B$4/12 -> 0.0125 | D21: =F21+E21 -> 44166.667 | E21: =B21*C21 -> 10833.333 | F21: =$B$8 -> 33333.333 | G21: =B21-F21 -> 833333.33 | J21: =D21+H21+I21 -> 44166.667 | K21: =J21/(1+$K$6/12)^A21 -> 37594.595
A22: =+A21+1 -> 12 | B22: =G21 -> 833333.33 | C22: =$B$4/12 -> 0.0125 | D22: =F22+E22 -> 43750 | E22: =B22*C22 -> 10416.667 | F22: =$B$8 -> 33333.333 | G22: =B22-F22 -> 800000 | J22: =D22+H22+I22 -> 43750 | K22: =J22/(1+$K$6/12)^A22 -> 36698.474
A23: =+A22+1 -> 13 | B23: =G22 -> 800000 | C23: =$B$4/12 -> 0.0125 | D23: =F23+E23 -> 43333.333 | E23: =B23*C23 -> 10000 | F23: =$B$8 -> 33333.333 | G23: =B23-F23 -> 766666.67 | I23: =I11 -> 12000 | J23: =D23+H23+I23 -> 55333.333 | K23: =J23/(1+$K$6/12)^A23 -> 45739.977
A24: =+A23+1 -> 14 | B24: =G23 -> 766666.67 | C24: =$B$4/12 -> 0.0125 | D24: =F24+E24 -> 42916.667 | E24: =B24*C24 -> 9583.3333 | F24: =$B$8 -> 33333.333 | G24: =B24-F24 -> 733333.33 | J24: =D24+H24+I24 -> 42916.667 | K24: =J24/(1+$K$6/12)^A24 -> 34960.228
A25: =+A24+1 -> 15 | B25: =G24 -> 733333.33 | C25: =$B$4/12 -> 0.0125 | D25: =F25+E25 -> 42500 | E25: =B25*C25 -> 9166.6667 | F25: =$B$8 -> 33333.333 | G25: =B25-F25 -> 700000 | J25: =D25+H25+I25 -> 42500 | K25: =J25/(1+$K$6/12)^A25 -> 34117.434
A26: =+A25+1 -> 16 | B26: =G25 -> 700000 | C26: =$B$4/12 -> 0.0125 | D26: =F26+E26 -> 42083.333 | E26: =B26*C26 -> 8750 | F26: =$B$8 -> 33333.333 | G26: =B26-F26 -> 666666.67 | J26: =D26+H26+I26 -> 42083.333 | K26: =J26/(1+$K$6/12)^A26 -> 33291.758
A27: =+A26+1 -> 17 | B27: =G26 -> 666666.67 | C27: =$B$4/12 -> 0.0125 | D27: =F27+E27 -> 41666.667 | E27: =B27*C27 -> 8333.3333 | F27: =$B$8 -> 33333.333 | G27: =B27-F27 -> 633333.33 | J27: =D27+H27+I27 -> 41666.667 | K27: =J27/(1+$K$6/12)^A27 -> 32482.879
A28: =+A27+1 -> 18 | B28: =G27 -> 633333.33 | C28: =$B$4/12 -> 0.0125 | D28: =F28+E28 -> 41250 | E28: =B28*C28 -> 7916.6667 | F28: =$B$8 -> 33333.333 | G28: =B28-F28 -> 600000 | J28: =D28+H28+I28 -> 41250 | K28: =J28/(1+$K$6/12)^A28 -> 31690.484
A29: =+A28+1 -> 19 | B29: =G28 -> 600000 | C29: =$B$4/12 -> 0.0125 | D29: =F29+E29 -> 40833.333 | E29: =B29*C29 -> 7500 | F29: =$B$8 -> 33333.333 | G29: =B29-F29 -> 566666.67 | J29: =D29+H29+I29 -> 40833.333 | K29: =J29/(1+$K$6/12)^A29 -> 30914.264
A30: =+A29+1 -> 20 | B30: =G29 -> 566666.67 | C30: =$B$4/12 -> 0.0125 | D30: =F30+E30 -> 40416.667 | E30: =B30*C30 -> 7083.3333 | F30: =$B$8 -> 33333.333 | G30: =B30-F30 -> 533333.33 | J30: =D30+H30+I30 -> 40416.667 | K30: =J30/(1+$K$6/12)^A30 -> 30153.917
A31: =+A30+1 -> 21 | B31: =G30 -> 533333.33 | C31: =$B$4/12 -> 0.0125 | D31: =F31+E31 -> 40000 | E31: =B31*C31 -> 6666.6667 | F31: =$B$8 -> 33333.333 | G31: =B31-F31 -> 500000 | J31: =D31+H31+I31 -> 40000 | K31: =J31/(1+$K$6/12)^A31 -> 29409.145
A32: =+A31+1 -> 22 | B32: =G31 -> 500000 | C32: =$B$4/12 -> 0.0125 | D32: =F32+E32 -> 39583.333 | E32: =B32*C32 -> 6250 | F32: =$B$8 -> 33333.333 | G32: =B32-F32 -> 466666.67 | J32: =D32+H32+I32 -> 39583.333 | K32: =J32/(1+$K$6/12)^A32 -> 28679.656
A33: =+A32+1 -> 23 | B33: =G32 -> 466666.67 | C33: =$B$4/12 -> 0.0125 | D33: =F33+E33 -> 39166.667 | E33: =B33*C33 -> 5833.3333 | F33: =$B$8 -> 33333.333 | G33: =B33-F33 -> 433333.33 | J33: =D33+H33+I33 -> 39166.667 | K33: =J33/(1+$K$6/12)^A33 -> 27965.162
A34: =+A33+1 -> 24 | B34: =G33 -> 433333.33 | C34: =$B$4/12 -> 0.0125 | D34: =F34+E34 -> 38750 | E34: =B34*C34 -> 5416.6667 | F34: =$B$8 -> 33333.333 | G34: =B34-F34 -> 400000 | J34: =D34+H34+I34 -> 38750 | K34: =J34/(1+$K$6/12)^A34 -> 27265.383
A35: =+A34+1 -> 25 | B35: =G34 -> 400000 | C35: =$B$4/12 -> 0.0125 | D35: =F35+E35 -> 38333.333 | E35: =B35*C35 -> 5000 | F35: =$B$8 -> 33333.333 | G35: =B35-F35 -> 366666.67 | I35: =I23 -> 12000 | J35: =D35+H35+I35 -> 50333.333 | K35: =J35/(1+$K$6/12)^A35 -> 34900.749
A36: =+A35+1 -> 26 | B36: =G35 -> 366666.67 | C36: =$B$4/12 -> 0.0125 | D36: =F36+E36 -> 37916.667 | E36: =B36*C36 -> 4583.3333 | F36: =$B$8 -> 33333.333 | G36: =B36-F36 -> 333333.33 | J36: =D36+H36+I36 -> 37916.667 | K36: =J36/(1+$K$6/12)^A36 -> 25908.864
A37: =+A36+1 -> 27 | B37: =G36 -> 333333.33 | C37: =$B$4/12 -> 0.0125 | D37: =F37+E37 -> 37500 | E37: =B37*C37 -> 4166.6667 | F37: =$B$8 -> 33333.333 | G37: =B37-F37 -> 300000 | J37: =D37+H37+I37 -> 37500 | K37: =J37/(1+$K$6/12)^A37 -> 25251.585
A38: =+A37+1 -> 28 | B38: =G37 -> 300000 | C38: =$B$4/12 -> 0.0125 | D38: =F38+E38 -> 37083.333 | E38: =B38*C38 -> 3750 | F38: =$B$8 -> 33333.333 | G38: =B38-F38 -> 266666.67 | J38: =D38+H38+I38 -> 37083.333 | K38: =J38/(1+$K$6/12)^A38 -> 24607.943
A39: =+A38+1 -> 29 | B39: =G38 -> 266666.67 | C39: =$B$4/12 -> 0.0125 | D39: =F39+E39 -> 36666.667 | E39: =B39*C39 -> 3333.3333 | F39: =$B$8 -> 33333.333 | G39: =B39-F39 -> 233333.33 | J39: =D39+H39+I39 -> 36666.667 | K39: =J39/(1+$K$6/12)^A39 -> 23977.679
A40: =+A39+1 -> 30 | B40: =G39 -> 233333.33 | C40: =$B$4/12 -> 0.0125 | D40: =F40+E40 -> 36250 | E40: =B40*C40 -> 2916.6667 | F40: =$B$8 -> 33333.333 | G40: =B40-F40 -> 200000 | J40: =D40+H40+I40 -> 36250 | K40: =J40/(1+$K$6/12)^A40 -> 23360.54
A41: =+A40+1 -> 31 | B41: =G40 -> 200000 | C41: =$B$4/12 -> 0.0125 | D41: =F41+E41 -> 35833.333 | E41: =B41*C41 -> 2500 | F41: =$B$8 -> 33333.333 | G41: =B41-F41 -> 166666.67 | J41: =D41+H41+I41 -> 35833.333 | K41: =J41/(1+$K$6/12)^A41 -> 22756.278
A42: =+A41+1 -> 32 | B42: =G41 -> 166666.67 | C42: =$B$4/12 -> 0.0125 | D42: =F42+E42 -> 35416.667 | E42: =B42*C42 -> 2083.3333 | F42: =$B$8 -> 33333.333 | G42: =B42-F42 -> 133333.33 | J42: =D42+H42+I42 -> 35416.667 | K42: =J42/(1+$K$6/12)^A42 -> 22164.65
A43: =+A42+1 -> 33 | B43: =G42 -> 133333.33 | C43: =$B$4/12 -> 0.0125 | D43: =F43+E43 -> 35000 | E43: =B43*C43 -> 1666.6667 | F43: =$B$8 -> 33333.333 | G43: =B43-F43 -> 100000 | J43: =D43+H43+I43 -> 35000 | K43: =J43/(1+$K$6/12)^A43 -> 21585.415
A44: =+A43+1 -> 34 | B44: =G43 -> 100000 | C44: =$B$4/12 -> 0.0125 | D44: =F44+E44 -> 34583.333 | E44: =B44*C44 -> 1250 | F44: =$B$8 -> 33333.333 | G44: =B44-F44 -> 66666.667 | J44: =D44+H44+I44 -> 34583.333 | K44: =J44/(1+$K$6/12)^A44 -> 21018.338
A45: =+A44+1 -> 35 | B45: =G44 -> 66666.667 | C45: =$B$4/12 -> 0.0125 | D45: =F45+E45 -> 34166.667 | E45: =B45*C45 -> 833.33333 | F45: =$B$8 -> 33333.333 | G45: =B45-F45 -> 33333.333 | J45: =D45+H45+I45 -> 34166.667 | K45: =J45/(1+$K$6/12)^A45 -> 20463.188
A46: =+A45+1 -> 36 | B46: =G45 -> 33333.333 | C46: =$B$4/12 -> 0.0125 | D46: =F46+E46 -> 33750 | E46: =B46*C46 -> 416.66667 | F46: =$B$8 -> 33333.333 | G46: =B46-F46 -> -2.1827873e-10 | J46: =D46+H46+I46 -> 33750 | K46: =J46/(1+$K$6/12)^A46 -> 19919.738

Sheet M. Supervivencia Pago Dec.
A1: Etapa del Crédito = | B1: 2 | F1: Probabilidad de Incumplimiento calculada con Puntajes
A2: Tasa Efectiva = | B2: =+'Crédito Pagos Decrecientes'!K6 -> 0.17704985
H3: Severidad de la Pérdidad mediante la fórmula de las notas
A4: Modelo de Supervivencia
E5: Supuesto | G5: Supuesto
A6: Tiempo | B6: Tasa r | C6: EIt | D6: Factor de Descuento | E6: PI | F6: PSt-1 | G6: SP | H6: Reserva
A7: 1 | B7: =$B$2 /12 -> 0.014754154 | C7: ='Crédito Pagos Decrecientes'!B11 -> 1200000 | D7: =1/(1+B7)^A7 -> 0.98546037 | E7: 0.12 | F7: =1-E7 -> 0.88 | G7: 0.45 | H7: =PRODUCT(C7:G7) -> 56194.892
A8: =+A7+1 -> 2 | B8: =$B$2 /12 -> 0.014754154 | C8: ='Crédito Pagos Decrecientes'!B12 -> 1166666.7 | D8: =1/(1+B8)^A8 -> 0.97113213 | E8: 0.12 | F8: =F7*(1-E8) -> 0.7744 | G8: 0.45 | H8: =PRODUCT(C8:G8) -> 47378.818
A9: =+A8+1 -> 3 | B9: =$B$2 /12 -> 0.014754154 | C9: ='Crédito Pagos Decrecientes'!B13 -> 1133333.3 | D9: =1/(1+B9)^A9 -> 0.95701223 | E9: 0.12 | F9: =F8*(1-E9) -> 0.681472 | G9: 0.45 | H9: =PRODUCT(C9:G9) -> 39913.235
A10: =+A9+1 -> 4 | B10: =$B$2 /12 -> 0.014754154 | C10: ='Crédito Pagos Decrecientes'!B14 -> 1100000 | D10: =1/(1+B10)^A10 -> 0.94309762 | E10: 0.12 | F10: =F9*(1-E10) -> 0.59969536 | G10: 0.45 | H10: =PRODUCT(C10:G10) -> 33594.933
A11: =+A10+1 -> 5 | B11: =$B$2 /12 -> 0.014754154 | C11: ='Crédito Pagos Decrecientes'!B15 -> 1066666.7 | D11: =1/(1+B11)^A11 -> 0.92938533 | E11: 0.12 | F11: =F10*(1-E11) -> 0.52773192 | G11: 0.45 | H11: =PRODUCT(C11:G11) -> 28250.859
A12: =+A11+1 -> 6 | B12: =$B$2 /12 -> 0.014754154 | C12: ='Crédito Pagos Decrecientes'!B16 -> 1033333.3 | D12: =1/(1+B12)^A12 -> 0.9158724 | E12: 0.12 | F12: =F11*(1-E12) -> 0.46440409 | G12: 0.45 | H12: =PRODUCT(C12:G12) -> 23733.687
A13: =+A12+1 -> 7 | B13: =$B$2 /12 -> 0.014754154 | C13: ='Crédito Pagos Decrecientes'!B17 -> 1000000 | D13: =1/(1+B13)^A13 -> 0.90255595 | E13: 0.12 | F13: =F12*(1-E13) -> 0.4086756 | G13: 0.45 | H13: =PRODUCT(C13:G13) -> 19918.04
A14: =+A13+1 -> 8 | B14: =$B$2 /12 -> 0.014754154 | C14: ='Crédito Pagos Decrecientes'!B18 -> 966666.67 | D14: =1/(1+B14)^A14 -> 0.88943312 | E14: 0.12 | F14: =F13*(1-E14) -> 0.35963452 | G14: 0.45 | H14: =PRODUCT(C14:G14) -> 16697.259
A15: =+A14+1 -> 9 | B15: =$B$2 /12 -> 0.014754154 | C15: ='Crédito Pagos Decrecientes'!B19 -> 933333.33 | D15: =1/(1+B15)^A15 -> 0.87650109 | E15: 0.12 | F15: =F14*(1-E15) -> 0.31647838 | G15: 0.45 | H15: =PRODUCT(C15:G15) -> 13980.64
A16: =+A15+1 -> 10 | B16: =$B$2 /12 -> 0.014754154 | C16: ='Crédito Pagos Decrecientes'!B20 -> 900000 | D16: =1/(1+B16)^A16 -> 0.86375709 | E16: 0.12 | F16: =F15*(1-E16) -> 0.27850098 | G16: 0.45 | H16: =PRODUCT(C16:G16) -> 11691.079
A17: =+A16+1 -> 11 | B17: =$B$2 /12 -> 0.014754154 | C17: ='Crédito Pagos Decrecientes'!B21 -> 866666.67 | D17: =1/(1+B17)^A17 -> 0.85119837 | E17: 0.12 | F17: =F16*(1-E17) -> 0.24508086 | G17: 0.45 | H17: =PRODUCT(C17:G17) -> 9763.0617
A18: =+A17+1 -> 12 | B18: =$B$2 /12 -> 0.014754154 | C18: ='Crédito Pagos Decrecientes'!B22 -> 833333.33 | D18: =1/(1+B18)^A18 -> 0.83882226 | E18: 0.12 | F18: =F17*(1-E18) -> 0.21567116 | G18: 0.45 | H18: =PRODUCT(C18:G18) -> 8140.9395
A19: =+A18+1 -> 13 | B19: =$B$2 /12 -> 0.014754154 | C19: ='Crédito Pagos Decrecientes'!B23 -> 800000 | D19: =1/(1+B19)^A19 -> 0.82662609 | E19: 0.12 | F19: =F18*(1-E19) -> 0.18979062 | G19: 0.45 | H19: =PRODUCT(C19:G19) -> 6777.4699
... A42: =+A41+1 -> 36 | B42: =$B$2 /12 -> 0.014754154 | C42: ='Crédito Pagos Decrecientes'!B46 -> 33333.333 | D42: =1/(1+B42)^A42 -> 0.59021446 | E42: 0.12 | F42: =F41*(1-E42) -> 0.010031738 | G42: 0.45 | H42: =PRODUCT(C42:G42) -> 10.657579
F44: Reserva lifetime = | H44: =SUM(H7:H42) -> 346861.85
F47: Reserva 12m =

Sheet Crédito Bullet
A1: Tabla de Amortización del Crédito Bullet
A3: Línea de Crédito | B3: 1000000
A4: Tasa del Crédito (Anual) | B4: 0.12
A5: Tiempo (n) | B5: 36 | C5: meses
A6: Tasa Comisión por Apertura | B6: 0.02 | J6: Tasa Efectiva | K6: 0.13873862
A7: Pagar Seguro (Anual) | B7: 10000
K8: =+SUM(K10:K45) -> 1000000
A9: Tiempo | B9: SI Inicio | C9: Tasa | D9: Pago = Cap + Intereses | E9: Interes. | F9: Pago a Capital | G9: SI Final | H9: Comisión por Apertura | I9: Seguro de Vida | J9: Pago Final | K9: Flujos a VP
A10: 1 | B10: =B3 -> 1000000 | C10: =$B$4/12 -> 0.01 | D10: =F10+E10 -> 10000 | E10: =B10*C10 -> 10000 | F10: =0 -> 0 | G10: =B10-F10 -> 1000000 | H10: =B10*B6 -> 20000 | I10: =B7 -> 10000 | J10: =D10+H10+I10 -> 40000 | K10: =J10/(1+$K$6/12)^A10 -> 39542.824
A11: =+A10+1 -> 2 | B11: =G10 -> 1000000 | C11: =$B$4/12 -> 0.01 | D11: =F11+E11 -> 10000 | E11: =B11*C11 -> 10000 | F11: =0 -> 0 | G11: =B11-F11 -> 1000000 | J11: =D11+H11+I11 -> 10000 | K11: =J11/(1+$K$6/12)^A11 -> 9772.7181
A12: =+A11+1 -> 3 | B12: =G11 -> 1000000 | C12: =$B$4/12 -> 0.01 | D12: =F12+E12 -> 10000 | E12: =B12*C12 -> 10000 | F12: =0 -> 0 | G12: =B12-F12 -> 1000000 | J12: =D12+H12+I12 -> 10000 | K12: =J12/(1+$K$6/12)^A12 -> 9661.0217
A13: =+A12+1 -> 4 | B13: =G12 -> 1000000 | C13: =$B$4/12 -> 0.01 | D13: =F13+E13 -> 10000 | E13: =B13*C13 -> 10000 | F13: =0 -> 0 | G13: =B13-F13 -> 1000000 | J13: =D13+H13+I13 -> 10000 | K13: =J13/(1+$K$6/12)^A13 -> 9550.6019
A14: =+A13+1 -> 5 | B14: =G13 -> 1000000 | C14: =$B$4/12 -> 0.01 | D14: =F14+E14 -> 10000 | E14: =B14*C14 -> 10000 | F14: =0 -> 0 | G14: =B14-F14 -> 1000000 | J14: =D14+H14+I14 -> 10000 | K14: =J14/(1+$K$6/12)^A14 -> 9441.4442
A15: =+A14+1 -> 6 | B15: =G14 -> 1000000 | C15: =$B$4/12 -> 0.01 | D15: =F15+E15 -> 10000 | E15: =B15*C15 -> 10000 | F15: =0 -> 0 | G15: =B15-F15 -> 1000000 | J15: =D15+H15+I15 -> 10000 | K15: =J15/(1+$K$6/12)^A15 -> 9333.534
A16: =+A15+1 -> 7 | B16: =G15 -> 1000000 | C16: =$B$4/12 -> 0.01 | D16: =F16+E16 -> 10000 | E16: =B16*C16 -> 10000 | F16: =0 -> 0 | G16: =B16-F16 -> 1000000 | J16: =D16+H16+I16 -> 10000 | K16: =J16/(1+$K$6/12)^A16 -> 9226.8573
A17: =+A16+1 -> 8 | B17: =G16 -> 1000000 | C17: =$B$4/12 -> 0.01 | D17: =F17+E17 -> 10000 | E17: =B17*C17 -> 10000 | F17: =0 -> 0 | G17: =B17-F17 -> 1000000 | J17: =D17+H17+I17 -> 10000 | K17: =J17/(1+$K$6/12)^A17 -> 9121.3997
A18: =+A17+1 -> 9 | B18: =G17 -> 1000000 | C18: =$B$4/12 -> 0.01 | D18: =F18+E18 -> 10000 | E18: =B18*C18 -> 10000 | F18: =0 -> 0 | G18: =B18-F18 -> 1000000 | J18: =D18+H18+I18 -> 10000 | K18: =J18/(1+$K$6/12)^A18 -> 9017.1475
A19: =+A18+1 -> 10 | B19: =G18 -> 1000000 | C19: =$B$4/12 -> 0.01 | D19: =F19+E19 -> 10000 | E19: =B19*C19 -> 10000 | F19: =0 -> 0 | G19: =B19-F19 -> 1000000 | J19: =D19+H19+I19 -> 10000 | K19: =J19/(1+$K$6/12)^A19 -> 8914.0868
A20: =+A19+1 -> 11 | B20: =G19 -> 1000000 | C20: =$B$4/12 -> 0.01 | D20: =F20+E20 -> 10000 | E20: =B20*C20 -> 10000 | F20: =0 -> 0 | G20: =B20-F20 -> 1000000 | J20: =D20+H20+I20 -> 10000 | K20: =J20/(1+$K$6/12)^A20 -> 8812.2041
A21: =+A20+1 -> 12 | B21: =G20 -> 1000000 | C21: =$B$4/12 -> 0.01 | D21: =F21+E21 -> 10000 | E21: =B21*C21 -> 10000 | F21: =0 -> 0 | G21: =B21-F21 -> 1000000 | J21: =D21+H21+I21 -> 10000 | K21: =J21/(1+$K$6/12)^A21 -> 8711.4858
A22: =+A21+1 -> 13 | B22: =G21 -> 1000000 | C22: =$B$4/12 -> 0.01 | D22: =F22+E22 -> 10000 | E22: =B22*C22 -> 10000 | F22: =0 -> 0 | G22: =B22-F22 -> 1000000 | I22: =I10 -> 10000 | J22: =D22+H22+I22 -> 20000 | K22: =J22/(1+$K$6/12)^A22 -> 17223.837
A23: =+A22+1 -> 14 | B23: =G22 -> 1000000 | C23: =$B$4/12 -> 0.01 | D23: =F23+E23 -> 10000 | E23: =B23*C23 -> 10000 | F23: =0 -> 0 | G23: =B23-F23 -> 1000000 | J23: =D23+H23+I23 -> 10000 | K23: =J23/(1+$K$6/12)^A23 -> 8513.4895
A24: =+A23+1 -> 15 | B24: =G23 -> 1000000 | C24: =$B$4/12 -> 0.01 | D24: =F24+E24 -> 10000 | E24: =B24*C24 -> 10000 | F24: =0 -> 0 | G24: =B24-F24 -> 1000000 | J24: =D24+H24+I24 -> 10000 | K24: =J24/(1+$K$6/12)^A24 -> 8416.1853
A25: =+A24+1 -> 16 | B25: =G24 -> 1000000 | C25: =$B$4/12 -> 0.01 | D25: =F25+E25 -> 10000 | E25: =B25*C25 -> 10000 | F25: =0 -> 0 | G25: =B25-F25 -> 1000000 | J25: =D25+H25+I25 -> 10000 | K25: =J25/(1+$K$6/12)^A25 -> 8319.9933
A26: =+A25+1 -> 17 | B26: =G25 -> 1000000 | C26: =$B$4/12 -> 0.01 | D26: =F26+E26 -> 10000 | E26: =B26*C26 -> 10000 | F26: =0 -> 0 | G26: =B26-F26 -> 1000000 | J26: =D26+H26+I26 -> 10000 | K26: =J26/(1+$K$6/12)^A26 -> 8224.9007
A27: =+A26+1 -> 18 | B27: =G26 -> 1000000 | C27: =$B$4/12 -> 0.01 | D27: =F27+E27 -> 10000 | E27: =B27*C27 -> 10000 | F27: =0 -> 0 | G27: =B27-F27 -> 1000000 | J27: =D27+H27+I27 -> 10000 | K27: =J27/(1+$K$6/12)^A27 -> 8130.8949
A28: =+A27+1 -> 19 | B28: =G27 -> 1000000 | C28: =$B$4/12 -> 0.01 | D28: =F28+E28 -> 10000 | E28: =B28*C28 -> 10000 | F28: =0 -> 0 | G28: =B28-F28 -> 1000000 | J28: =D28+H28+I28 -> 10000 | K28: =J28/(1+$K$6/12)^A28 -> 8037.9636
A29: =+A28+1 -> 20 | B29: =G28 -> 1000000 | C29: =$B$4/12 -> 0.01 | D29: =F29+E29 -> 10000 | E29: =B29*C29 -> 10000 | F29: =0 -> 0 | G29: =B29-F29 -> 1000000 | J29: =D29+H29+I29 -> 10000 | K29: =J29/(1+$K$6/12)^A29 -> 7946.0944
A30: =+A29+1 -> 21 | B30: =G29 -> 1000000 | C30: =$B$4/12 -> 0.01 | D30: =F30+E30 -> 10000 | E30: =B30*C30 -> 10000 | F30: =0 -> 0 | G30: =B30-F30 -> 1000000 | J30: =D30+H30+I30 -> 10000 | K30: =J30/(1+$K$6/12)^A30 -> 7855.2752
A31: =+A30+1 -> 22 | B31: =G30 -> 1000000 | C31: =$B$4/12 -> 0.01 | D31: =F31+E31 -> 10000 | E31: =B31*C31 -> 10000 | F31: =0 -> 0 | G31: =B31-F31 -> 1000000 | J31: =D31+H31+I31 -> 10000 | K31: =J31/(1+$K$6/12)^A31 -> 7765.4941
A32: =+A31+1 -> 23 | B32: =G31 -> 1000000 | C32: =$B$4/12 -> 0.01 | D32: =F32+E32 -> 10000 | E32: =B32*C32 -> 10000 | F32: =0 -> 0 | G32: =B32-F32 -> 1000000 | J32: =D32+H32+I32 -> 10000 | K32: =J32/(1+$K$6/12)^A32 -> 7676.7391
A33: =+A32+1 -> 24 | B33: =G32 -> 1000000 | C33: =$B$4/12 -> 0.01 | D33: =F33+E33 -> 10000 | E33: =B33*C33 -> 10000 | F33: =0 -> 0 | G33: =B33-F33 -> 1000000 | J33: =D33+H33+I33 -> 10000 | K33: =J33/(1+$K$6/12)^A33 -> 7588.9985
A34: =+A33+1 -> 25 | B34: =G33 -> 1000000 | C34: =$B$4/12 -> 0.01 | D34: =F34+E34 -> 10000 | E34: =B34*C34 -> 10000 | F34: =0 -> 0 | G34: =B34-F34 -> 1000000 | I34: =I22 -> 10000 | J34: =D34+H34+I34 -> 20000 | K34: =J34/(1+$K$6/12)^A34 -> 15004.521
A35: =+A34+1 -> 26 | B35: =G34 -> 1000000 | C35: =$B$4/12 -> 0.01 | D35: =F35+E35 -> 10000 | E35: =B35*C35 -> 10000 | F35: =0 -> 0 | G35: =B35-F35 -> 1000000 | J35: =D35+H35+I35 -> 10000 | K35: =J35/(1+$K$6/12)^A35 -> 7416.5143
A36: =+A35+1 -> 27 | B36: =G35 -> 1000000 | C36: =$B$4/12 -> 0.01 | D36: =F36+E36 -> 10000 | E36: =B36*C36 -> 10000 | F36: =0 -> 0 | G36: =B36-F36 -> 1000000 | J36: =D36+H36+I36 -> 10000 | K36: =J36/(1+$K$6/12)^A36 -> 7331.7479
A37: =+A36+1 -> 28 | B37: =G36 -> 1000000 | C37: =$B$4/12 -> 0.01 | D37: =F37+E37 -> 10000 | E37: =B37*C37 -> 10000 | F37: =0 -> 0 | G37: =B37-F37 -> 1000000 | J37: =D37+H37+I37 -> 10000 | K37: =J37/(1+$K$6/12)^A37 -> 7247.9503
A38: =+A37+1 -> 29 | B38: =G37 -> 1000000 | C38: =$B$4/12 -> 0.01 | D38: =F38+E38 -> 10000 | E38: =B38*C38 -> 10000 | F38: =0 -> 0 | G38: =B38-F38 -> 1000000 | J38: =D38+H38+I38 -> 10000 | K38: =J38/(1+$K$6/12)^A38 -> 7165.1105
A39: =+A38+1 -> 30 | B39: =G38 -> 1000000 | C39: =$B$4/12 -> 0.01 | D39: =F39+E39 -> 10000 | E39: =B39*C39 -> 10000 | F39: =0 -> 0 | G39: =B39-F39 -> 1000000 | J39: =D39+H39+I39 -> 10000 | K39: =J39/(1+$K$6/12)^A39 -> 7083.2175
A40: =+A39+1 -> 31 | B40: =G39 -> 1000000 | C40: =$B$4/12 -> 0.01 | D40: =F40+E40 -> 10000 | E40: =B40*C40 -> 10000 | F40: =0 -> 0 | G40: =B40-F40 -> 1000000 | J40: =D40+H40+I40 -> 10000 | K40: =J40/(1+$K$6/12)^A40 -> 7002.2606
A41: =+A40+1 -> 32 | B41: =G40 -> 1000000 | C41: =$B$4/12 -> 0.01 | D41: =F41+E41 -> 10000 | E41: =B41*C41 -> 10000 | F41: =0 -> 0 | G41: =B41-F41 -> 1000000 | J41: =D41+H41+I41 -> 10000 | K41: =J41/(1+$K$6/12)^A41 -> 6922.2288
A42: =+A41+1 -> 33 | B42: =G41 -> 1000000 | C42: =$B$4/12 -> 0.01 | D42: =F42+E42 -> 10000 | E42: =B42*C42 -> 10000 | F42: =0 -> 0 | G42: =B42-F42 -> 1000000 | J42: =D42+H42+I42 -> 10000 | K42: =J42/(1+$K$6/12)^A42 -> 6843.1119
A43: =+A42+1 -> 34 | B43: =G42 -> 1000000 | C43: =$B$4/12 -> 0.01 | D43: =F43+E43 -> 10000 | E43: =B43*C43 -> 10000 | F43: =0 -> 0 | G43: =B43-F43 -> 1000000 | J43: =D43+H43+I43 -> 10000 | K43: =J43/(1+$K$6/12)^A43 -> 6764.8991
A44: =+A43+1 -> 35 | B44: =G43 -> 1000000 | C44: =$B$4/12 -> 0.01 | D44: =F44+E44 -> 10000 | E44: =B44*C44 -> 10000 | F44: =0 -> 0 | G44: =B44-F44 -> 1000000 | J44: =D44+H44+I44 -> 10000 | K44: =J44/(1+$K$6/12)^A44 -> 6687.5803
A45: =+A44+1 -> 36 | B45: =G44 -> 1000000 | C45: =$B$4/12 -> 0.01 | D45: =F45+E45 -> 1010000 | E45: =B45*C45 -> 10000 | F45: =B3 -> 1000000 | G45: =B45-F45 -> 0 | J45: =D45+H45+I45 -> 1010000 | K45: =J45/(1+$K$6/12)^A45 -> 667725.67

Sheet M. Supervivencia Bullet
A1: Etapa del Crédito = | B1: 2 | F1: Probabilidad de Incumplimiento calculada con Puntajes
A2: Tasa Efectiva = | B2: =+'Crédito Bullet'!K6 -> 0.13873862
H3: Severidad de la Pérdidad mediante la fórmula de las notas
A4: Modelo de Supervivencia
E5: Supuesto | G5: Supuesto
A6: Tiempo | B6: Tasa r | C6: EIt | D6: Factor de Descuento | E6: PI | F6: PSt-1 | G6: SP | H6: Reserva
A7: 1 | B7: =$B$2 /12 -> 0.011561552 | C7: ='Crédito Bullet'!B10 -> 1000000 | D7: =1/(1+B7)^A7 -> 0.98857059 | E7: 0.2 | F7: =1-E7 -> 0.8 | G7: 0.45 | H7: =PRODUCT(C7:G7) -> 71177.082
A8: =+A7+1 -> 2 | B8: =$B$2 /12 -> 0.011561552 | C8: ='Crédito Bullet'!B11 -> 1000000 | D8: =1/(1+B8)^A8 -> 0.97727181 | E8: 0.2 | F8: =F7*(1-E8) -> 0.64 | G8: 0.45 | H8: =PRODUCT(C8:G8) -> 56290.856
A9: =+A8+1 -> 3 | B9: =$B$2 /12 -> 0.011561552 | C9: ='Crédito Bullet'!B12 -> 1000000 | D9: =1/(1+B9)^A9 -> 0.96610217 | E9: 0.2 | F9: =F8*(1-E9) -> 0.512 | G9: 0.45 | H9: =PRODUCT(C9:G9) -> 44517.988
A10: =+A9+1 -> 4 | B10: =$B$2 /12 -> 0.011561552 | C10: ='Crédito Bullet'!B13 -> 1000000 | D10: =1/(1+B10)^A10 -> 0.95506019 | E10: 0.2 | F10: =F9*(1-E10) -> 0.4096 | G10: 0.45 | H10: =PRODUCT(C10:G10) -> 35207.339
A11: =+A10+1 -> 5 | B11: =$B$2 /12 -> 0.011561552 | C11: ='Crédito Bullet'!B14 -> 1000000 | D11: =1/(1+B11)^A11 -> 0.94414442 | E11: 0.2 | F11: =F10*(1-E11) -> 0.32768 | G11: 0.45 | H11: =PRODUCT(C11:G11) -> 27843.952
A12: =+A11+1 -> 6 | B12: =$B$2 /12 -> 0.011561552 | C12: ='Crédito Bullet'!B15 -> 1000000 | D12: =1/(1+B12)^A12 -> 0.9333534 | E12: 0.2 | F12: =F11*(1-E12) -> 0.262144 | G12: 0.45 | H12: =PRODUCT(C12:G12) -> 22020.57
A13: =+A12+1 -> 7 | B13: =$B$2 /12 -> 0.011561552 | C13: ='Crédito Bullet'!B16 -> 1000000 | D13: =1/(1+B13)^A13 -> 0.92268573 | E13: 0.2 | F13: =F12*(1-E13) -> 0.2097152 | G13: 0.45 | H13: =PRODUCT(C13:G13) -> 17415.11
A14: =+A13+1 -> 8 | B14: =$B$2 /12 -> 0.011561552 | C14: ='Crédito Bullet'!B17 -> 1000000 | D14: =1/(1+B14)^A14 -> 0.91213997 | E14: 0.2 | F14: =F13*(1-E14) -> 0.16777216 | G14: 0.45 | H14: =PRODUCT(C14:G14) -> 13772.852
A15: =+A14+1 -> 9 | B15: =$B$2 /12 -> 0.011561552 | C15: ='Crédito Bullet'!B18 -> 1000000 | D15: =1/(1+B15)^A15 -> 0.90171475 | E15: 0.2 | F15: =F14*(1-E15) -> 0.13421773 | G15: 0.45 | H15: =PRODUCT(C15:G15) -> 10892.349
A16: =+A15+1 -> 10 | B16: =$B$2 /12 -> 0.011561552 | C16: ='Crédito Bullet'!B19 -> 1000000 | D16: =1/(1+B16)^A16 -> 0.89140868 | E16: 0.2 | F16: =F15*(1-E16) -> 0.10737418 | G16: 0.45 | H16: =PRODUCT(C16:G16) -> 8614.2851
A17: =+A16+1 -> 11 | B17: =$B$2 /12 -> 0.011561552 | C17: ='Crédito Bullet'!B20 -> 1000000 | D17: =1/(1+B17)^A17 -> 0.88122041 | E17: 0.2 | F17: =F16*(1-E17) -> 0.085899346 | G17: 0.45 | H17: =PRODUCT(C17:G17) -> 6812.6631
A18: =+A17+1 -> 12 | B18: =$B$2 /12 -> 0.011561552 | C18: ='Crédito Bullet'!B21 -> 1000000 | D18: =1/(1+B18)^A18 -> 0.87114858 | E18: 0.2 | F18: =F17*(1-E18) -> 0.068719477 | G18: 0.45 | H18: =PRODUCT(C18:G18) -> 5387.8387
A19: =+A18+1 -> 13 | B19: =$B$2 /12 -> 0.011561552 | C19: ='Crédito Bullet'!B22 -> 1000000 | D19: =1/(1+B19)^A19 -> 0.86119186 | E19: 0.2 | F19: =F18*(1-E19) -> 0.054975581 | G19: 0.45 | H19: =PRODUCT(C19:G19) -> 4261.0071
... A42: =+A41+1 -> 36 | B42: =$B$2 /12 -> 0.011561552 | C42: ='Crédito Bullet'!B45 -> 1000000 | D42: =1/(1+B42)^A42 -> 0.66111452 | E42: 0.2 | F42: =F41*(1-E42) -> 0.00032451855 | G42: 0.45 | H42: =PRODUCT(C42:G42) -> 19.308954
F44: Reserva lifetime = | H44: =SUM(H7:H42) -> 340253.47
F47: Reserva 12m =
